mkdocs_gen_files/__init__.py
mkdocs_gen_files/editor.py
mkdocs_gen_files/nav.py
mkdocs_gen_files/plugin.py
mkdocs_gen_files-0.3.5.dist-info/entry_points.txt
mkdocs_gen_files-0.3.5.dist-info/LICENSE.md
mkdocs_gen_files-0.3.5.dist-info/WHEEL
mkdocs_gen_files-0.3.5.dist-info/METADATA
mkdocs_gen_files-0.3.5.dist-info/RECORD
