Metadata-Version: 2.1
Name: mkdocs-gen-files
Version: 0.3.5
Summary: MkDocs plugin to programmatically generate documentation pages during the build
Home-page: https://github.com/oprypin/mkdocs-gen-files
License: MIT
Keywords: mkdocs,mkdocs-plugin
Author: Oleh Prypin
Author-email: oleh@pryp.in
Requires-Python: >=3.7,<4.0
Classifier: License :: OSI Approved :: MIT License
Classifier: Programming Language :: Python :: 3
Classifier: Programming Language :: Python :: 3.10
Classifier: Programming Language :: Python :: 3.7
Classifier: Programming Language :: Python :: 3.8
Classifier: Programming Language :: Python :: 3.9
Requires-Dist: mkdocs (>=1.0.3,<2.0.0)
Project-URL: Repository, https://github.com/oprypin/mkdocs-gen-files
